<?xml version="1.0" encoding="utf-8"?>
<GameData>
	<Building_YieldChanges>
		<Row>
			<BuildingType>BUILDING_QADI_COURT</BuildingType>
			<YieldType>YIELD_FAITH</YieldType>
			<Yield>2</Yield>
		</Row>
	</Building_YieldChanges>

	<Building_Flavors>
		<Row>
			<BuildingType>BUILDING_QADI_COURT</BuildingType>
			<FlavorType>FLAVOR_CULTURE</FlavorType>
			<Flavor>30</Flavor>
		</Row>
		<Row>
			<BuildingType>BUILDING_QADI_COURT</BuildingType>
			<FlavorType>FLAVOR_HAPPINESS</FlavorType>
			<Flavor>60</Flavor>
		</Row>
		<Row>
			<BuildingType>BUILDING_QADI_COURT</BuildingType>
			<FlavorType>FLAVOR_GOLD</FlavorType>
			<Flavor>10</Flavor>
		</Row>
		<Row>
			<BuildingType>BUILDING_QADI_COURT</BuildingType>
			<FlavorType>FLAVOR_RELIGION</FlavorType>
			<Flavor>20</Flavor>
		</Row>
	</Building_Flavors>

	<Civilization_BuildingClassOverrides>
		<Row>
			<CivilizationType>CIVILIZATION_SONGHAI</CivilizationType>
			<BuildingClassType>BUILDINGCLASS_COURTHOUSE</BuildingClassType>
			<BuildingType>BUILDING_QADI_COURT</BuildingType>
		</Row>
	</Civilization_BuildingClassOverrides>
</GameData>
